setup.py
admcheck.egg-info/PKG-INFO
admcheck.egg-info/SOURCES.txt
admcheck.egg-info/dependency_links.txt
admcheck.egg-info/requires.txt
admcheck.egg-info/top_level.txt
libname/__init__.py
libname/hello.py